odoo/addons/partner_multi_relation_tabs/README.rst
odoo/addons/partner_multi_relation_tabs/__init__.py
odoo/addons/partner_multi_relation_tabs/__manifest__.py
odoo/addons/partner_multi_relation_tabs/demo/res_partner_category_demo.xml
odoo/addons/partner_multi_relation_tabs/demo/res_partner_demo.xml
odoo/addons/partner_multi_relation_tabs/demo/res_partner_relation_demo.xml
odoo/addons/partner_multi_relation_tabs/demo/res_partner_relation_type_demo.xml
odoo/addons/partner_multi_relation_tabs/demo/res_partner_tab_demo.xml
odoo/addons/partner_multi_relation_tabs/i18n/da.po
odoo/addons/partner_multi_relation_tabs/i18n/it.po
odoo/addons/partner_multi_relation_tabs/i18n/nl.po
odoo/addons/partner_multi_relation_tabs/i18n/partner_multi_relation_tabs.pot
odoo/addons/partner_multi_relation_tabs/models/__init__.py
odoo/addons/partner_multi_relation_tabs/models/res_partner.py
odoo/addons/partner_multi_relation_tabs/models/res_partner_relation_all.py
odoo/addons/partner_multi_relation_tabs/models/res_partner_relation_type.py
odoo/addons/partner_multi_relation_tabs/models/res_partner_relation_type_selection.py
odoo/addons/partner_multi_relation_tabs/models/res_partner_tab.py
odoo/addons/partner_multi_relation_tabs/models/res_partner_tab_sequence.py
odoo/addons/partner_multi_relation_tabs/readme/CONTRIBUTORS.rst
odoo/addons/partner_multi_relation_tabs/readme/DESCRIPTION.rst
odoo/addons/partner_multi_relation_tabs/readme/USAGE.rst
odoo/addons/partner_multi_relation_tabs/security/ir.model.access.csv
odoo/addons/partner_multi_relation_tabs/static/description/icon.png
odoo/addons/partner_multi_relation_tabs/static/description/index.html
odoo/addons/partner_multi_relation_tabs/static/description/partner_multi_relation_tabs-partner-display.png
odoo/addons/partner_multi_relation_tabs/static/description/partner_multi_relation_tabs-partner-edit.png
odoo/addons/partner_multi_relation_tabs/static/description/partner_multi_relation_tabs-relation-search.png
odoo12_addon_partner_multi_relation_tabs-12.0.2.0.0.dist-info/METADATA
odoo12_addon_partner_multi_relation_tabs-12.0.2.0.0.dist-info/WHEEL
odoo12_addon_partner_multi_relation_tabs-12.0.2.0.0.dist-info/top_level.txt
odoo12_addon_partner_multi_relation_tabs-12.0.2.0.0.dist-info/RECORD
