Metadata-Version: 2.1
Name: odoo12-addon-partner-multi-relation-tabs
Version: 12.0.2.0.0
Summary: Show partner relations in own tab
Home-page: UNKNOWN
Author: Therp BV,Odoo Community Association (OCA)
Author-email: support@odoo-community.org
License: AGPL-3
Platform: UNKNOWN
Classifier: Programming Language :: Python
Classifier: Framework :: Odoo
Classifier: Framework :: Odoo :: 12.0
Classifier: License :: OSI Approved :: GNU Affero General Public License v3
Requires-Python: >=3.5
Requires-Dist: odoo12-addon-partner-multi-relation
Requires-Dist: odoo (<12.1dev,>=12.0a)
